netsec/__init__.py
netsec/analyzer.py
netsec/requirements.txt
netsec/modules/att.py
netsec/modules/email_template.html
netsec/modules/helper.py
netsec/modules/models.py
netsec/modules/netgear.py
netsec/modules/settings.py
NetSec-0.9.1.dist-info/LICENSE
NetSec-0.9.1.dist-info/METADATA
NetSec-0.9.1.dist-info/WHEEL
NetSec-0.9.1.dist-info/top_level.txt
NetSec-0.9.1.dist-info/RECORD
