Metadata-Version: 2.1
Name: NetSec
Version: 0.9.1
Summary: Python module to analyze devices connected to the router and alert accordingly.
Author-email: Vignesh Sivanandha Rao <svignesh1793@gmail.com>
License: MIT License
Project-URL: Homepage, https://github.com/thevickypedia/NetSec
Project-URL: Docs, https://thevickypedia.github.io/NetSec/
Project-URL: Source, https://github.com/thevickypedia/NetSec
Project-URL: Bug Tracker, https://github.com/thevickypedia/NetSec/issues
Project-URL: Release Notes, https://github.com/thevickypedia/NetSec/blob/main/release_notes.rst
Keywords: NetSec,network-security,lan,wlan
Classifier: License :: OSI Approved :: MIT License
Classifier: Programming Language :: Python :: 3
Classifier: Development Status :: 5 - Production/Stable
Classifier: Operating System :: MacOS :: MacOS X
Classifier: Operating System :: Microsoft :: Windows
Classifier: Operating System :: POSIX :: Linux
Classifier: Topic :: System :: Networking :: Firewalls
Classifier: Topic :: System :: Networking :: Monitoring :: Hardware Watchdog
Requires-Python: >=3.8
License-File: LICENSE
Requires-Dist: pynetgear ==0.10.9
Requires-Dist: python-dotenv
Requires-Dist: pytz
Requires-Dist: PyYAML
Requires-Dist: requests
Requires-Dist: pandas
Requires-Dist: lxml
Requires-Dist: gmail-connector
Requires-Dist: Jinja2
Provides-Extra: dev
Requires-Dist: sphinx ==5.1.1 ; extra == 'dev'
Requires-Dist: pre-commit ; extra == 'dev'
Requires-Dist: recommonmark ; extra == 'dev'
Requires-Dist: gitverse ; extra == 'dev'
